gepir/__init__.py
gepir/elements.py
gepir/errors.py
gepir-4.0.9.dist-info/LICENSE
gepir-4.0.9.dist-info/METADATA
gepir-4.0.9.dist-info/WHEEL
gepir-4.0.9.dist-info/entry_points.txt
gepir-4.0.9.dist-info/top_level.txt
gepir-4.0.9.dist-info/RECORD
