Metadata-Version: 2.1
Name: gepir
Version: 4.0.9
Summary: A python client package for querying GEPIR.
Home-page: https://bitbucket.com/davebelais/gepir
Author: David Belais
Author-email: david@belais.me
License: MIT
Keywords: gepir gs1 gtin gln gcp
Platform: UNKNOWN
Classifier: Development Status :: 4 - Beta
Classifier: Intended Audience :: Developers
Classifier: License :: OSI Approved :: MIT License
Classifier: Programming Language :: Python :: 2.7
Classifier: Programming Language :: Python :: 3.4
Classifier: Programming Language :: Python :: 3.5
Classifier: Programming Language :: Python :: 3.6
Requires-Dist: future (>=0.17.0)
Requires-Dist: iso8601 (>=0.1.12)
Provides-Extra: dev
Requires-Dist: pytest (>=2.9.0); extra == 'dev'
Provides-Extra: test
Requires-Dist: pytest (>=2.9.0); extra == 'test'
